fdtooldf/__init__.py
fdtooldf/fdtool.py
fdtooldf/modules/Apriori_Gen.py
fdtooldf/modules/GetFDs.py
fdtooldf/modules/ObtainEquivalences.py
fdtooldf/modules/Prune.py
fdtooldf/modules/__init__.py
fdtooldf/modules/binaryRepr.py
fdtooldf/modules/dbschema/__init__.py
fdtooldf/modules/dbschema/dbschema.py
fdtooldf/modules/keyRun.py
fdtooldf/runner.py
fdtooldf/utils.py
fdtooldf-0.0.1.dist-info/METADATA
fdtooldf-0.0.1.dist-info/WHEEL
fdtooldf-0.0.1.dist-info/RECORD
