Metadata-Version: 2.1
Name: fdtooldf
Version: 0.0.1
Summary: Mine for functional dependencies in dataframes with polars
Author: Grigory T
Requires-Python: >=3.8,<4.0
Classifier: Programming Language :: Python :: 3
Classifier: Programming Language :: Python :: 3.8
Classifier: Programming Language :: Python :: 3.9
Classifier: Programming Language :: Python :: 3.10
Classifier: Programming Language :: Python :: 3.11
Classifier: Programming Language :: Python :: 3.12
Classifier: Programming Language :: Python :: 3.13
Requires-Dist: pandas
Requires-Dist: polars
